README.md
setup.cfg
setup.py
src/InstagramFakeAPI/__init__.py
src/InstagramFakeAPI.egg-info/PKG-INFO
src/InstagramFakeAPI.egg-info/SOURCES.txt
src/InstagramFakeAPI.egg-info/dependency_links.txt
src/InstagramFakeAPI.egg-info/top_level.txt
src/InstagramFakeAPI/lib/__init__.py
src/InstagramFakeAPI/lib/constant/__init__.py
src/InstagramFakeAPI/lib/constant/header.py
src/InstagramFakeAPI/lib/email/__init__.py
src/InstagramFakeAPI/lib/email/pop.py
src/InstagramFakeAPI/lib/entity/__init__.py
src/InstagramFakeAPI/lib/entity/credential.py
src/InstagramFakeAPI/lib/exception/__init__.py
src/InstagramFakeAPI/lib/exception/account.py
src/InstagramFakeAPI/lib/exception/main.py
src/InstagramFakeAPI/lib/mixin/__init__.py
src/InstagramFakeAPI/lib/mixin/request.py
src/InstagramFakeAPI/lib/util/__init__.py
src/InstagramFakeAPI/lib/util/abstract.py
src/InstagramFakeAPI/lib/util/challenge.py
src/InstagramFakeAPI/lib/util/crypto.py
src/InstagramFakeAPI/lib/util/generator.py
src/InstagramFakeAPI/v159/__init__.py
src/InstagramFakeAPI/v159/entity/__init__.py
src/InstagramFakeAPI/v159/entity/credential.py
src/InstagramFakeAPI/v159/mixin/__init__.py
src/InstagramFakeAPI/v159/mixin/action.py
src/InstagramFakeAPI/v159/mixin/login.py
src/InstagramFakeAPI/v159/mixin/request.py
src/InstagramFakeAPI/v159/utils/__init__.py
src/InstagramFakeAPI/v159/utils/header.py
src/InstagramFakeAPI/v187/__init__.py
src/InstagramFakeAPI/v187/entity/__init__.py
src/InstagramFakeAPI/v187/entity/credential.py
src/InstagramFakeAPI/v187/mixin/__init__.py
src/InstagramFakeAPI/v187/mixin/action.py
src/InstagramFakeAPI/v187/mixin/login.py
src/InstagramFakeAPI/v187/mixin/request.py
src/InstagramFakeAPI/v187/utils/__init__.py
src/InstagramFakeAPI/v187/utils/header.py