Metadata-Version: 2.1
Name: InstagramFakeAPI
Version: 0.1.12
Summary: Endemic Instagram API Wrapper
Home-page: 
Author: Dima Denisov
Author-email: python@endemic.ru
License: MIT
Platform: UNKNOWN
Classifier: License :: OSI Approved :: MIT License
Classifier: Programming Language :: Python :: 3
Classifier: Programming Language :: Python :: 3.7
